{"surah":74,"edition":"ur.junagarhi","generatedAt":"2026-07-18T03:31:31.081Z","gaps":0,"ayahs":[{"number":1,"translation":"اے کپڑا اوڑھنے والے","words":["اے","اوڑھ لپیٹ کر لیٹنے والے"]},{"number":2,"translation":"کھڑا ہوجا اور آگاه کردے","words":["کھڑے ہوجاؤ","پھر خبردار کرو"]},{"number":3,"translation":"اور اپنے رب ہی کی بڑائیاں بیان کر","words":["اور اپنے رب کی","پس بڑائی بیان کرو"]},{"number":4,"translation":"اپنے کپڑوں کو پاک رکھا کر","words":["اور اپنے کپڑے","پس پاک رکھو"]},{"number":5,"translation":"ناپاکی کو چھوڑ دے","words":["اور گندگی","پس چھوڑ دو"]},{"number":6,"translation":"اور احسان کرکے زیاده لینے کی خواہش نہ کر","words":["اور نہ","تم احسان کرو","تم زیادہ حاصل کرسکو"]},{"number":7,"translation":"اور اپنے رب کی راه میں صبر کر","words":["اور اپنے رب کے لیے","پس صبر کرو"]},{"number":8,"translation":"پس جب کہ صور میں پھونک ماری جائے گی","words":["پھر جب","پھونکا جائے گا","میں","صور"]},{"number":9,"translation":"تو وه دن بڑا سخت دن ہوگا","words":["تو یہ","اس دن","ایک دن  ہوگا","سخت"]},{"number":10,"translation":"جو کافروں پر آسان نہ ہوگا","words":["پر","کافروں","نہ","آسان ہوگا"]},{"number":11,"translation":"مجھے اور اسے چھوڑ دے جسے میں نے اکیلا پیدا کیا ہے","words":["چھوڑ دو مجھ کو","اور جس کو","میں نے پیدا کیا","اکیلے"]},{"number":12,"translation":"اور اسے بہت سا مال دے رکھا ہے","words":["اور میں نے بنایا","اس کے لیے","مال","بہت"]},{"number":13,"translation":"اور حاضر باش فرزند بھی","words":["اور بیٹے","حاضر رہنے والے"]},{"number":14,"translation":"اور میں نے اسے بہت کچھ کشادگی دے رکھی ہے","words":["اور میں نے بچھایا","اس کے لیے","بچھونا"]},{"number":15,"translation":"پھر بھی اس کی چاہت ہے کہ میں اسے اور زیاده دوں","words":["پھر","وہ طمع رکھتا ہے۔ امید رکھتا ہے","کہ","(اور) زیادہ دوں"]},{"number":16,"translation":"نہیں نہیں، وه ہماری آیتوں کا مخالف ہے","words":["ہرگز نہیں","بیشک وہ","ہے","ہماری آیات کے لیے","عناد رکھنے والا"]},{"number":17,"translation":"عنقریب میں اسے ایک سخت چڑھائی چڑھاؤں گا","words":["عنقریب میں چڑھاؤں گا اس کو","کٹھن چڑھائی"]},{"number":18,"translation":"اس نے غور کرکے تجویز کی","words":["بیشک اس نے","سوچا","اور اندازہ"]},{"number":19,"translation":"اسے ہلاکت ہو کیسی (تجویز) سوچی؟","words":["پس مارا جائے","کس طرح","اس نے اندازہ کیا"]},{"number":20,"translation":"وه پھر غارت ہو کس طرح اندازه کیا","words":["پھر","مارا جائے","کس طرح","اس نے اندازہ کیا"]},{"number":21,"translation":"اس نے پھر دیکھا","words":["پھر","اس نے دیکھا"]},{"number":22,"translation":"پھر تیوری چڑھائی اور منھ بنایا","words":["پھر","اس نے تیوری چڑھائی","اور منہ بسورا"]},{"number":23,"translation":"پھر پیچھے ہٹ گیا اور غرور کیا","words":["پھر","پلٹا","اور تکبر کیا"]},{"number":24,"translation":"اور کہنے لگا تو یہ صرف جادو ہے جو نقل کیا جاتا ہے","words":["پھر کہا","نہیں","یہ","مگر","ایک جادو ہے","جو پہلے سے چلا آرہا ہے"]},{"number":25,"translation":"سوائے انسانی کلام کے کچھ بھی نہیں ہے","words":["نہیں","یہ","مگر","بات","ایک انسان کی"]},{"number":26,"translation":"میں عنقریب اسے دوزخ میں ڈالوں گا","words":["عنقریب میں جھونکوں گا اس کو۔ ڈالوں گا اس کو","دوزخ میں"]},{"number":27,"translation":"اور تجھے کیا خبر کہ دوزخ کیا چیز ہے؟","words":["اور کیا چیز","بتائے تجھ کو","کیا ہے","دوزخ"]},{"number":28,"translation":"نہ وه باقی رکھتی ہے نہ چھوڑتی ہے","words":["نہ","باقی رکھے","اور نہ","چھوڑے"]},{"number":29,"translation":"کھال کو جھلسا دیتی ہے","words":["جھلسا دینے والی ہے","بدن کو۔ جسم کو"]},{"number":30,"translation":"اور اس میں انیس (فرشتے مقرر) ہیں","words":["اس پر","نو","دس (انیس ہیں)"]},{"number":31,"translation":"ہم نے دوزخ کے داروغے صرف فرشتے رکھے ہیں۔ اور ہم نے ان کی تعداد صرف کافروں کی آزمائش کے لیے مقرر کی ہے تاکہ اہل کتاب یقین کرلیں، اوراہل ایمان کے ایمان میں اضافہ ہو جائے اور اہل کتاب اور اہل ایمان شک نہ کریں اور جن کے دلوں میں بیماری ہے وه اور کافر کہیں کہ اس بیان سے اللہ تعالیٰ کی کیا مراد ہے؟ اسی طرح اللہ تعالیٰ جسے چاہتا ہے گمراه کرتا ہے اور جسے چاہتا ہے ہدایت دیتا ہے۔ تیرے رب کے لشکروں کو اس کے سوا کوئی نہیں جانتا، یہ تو کل بنی آدم کے لیے سراسر پند ونصیحت ہے","words":["اور نہیں","بنایا ہم نے","ساتھی","آگ (والوں کو)","مگر","فرشتے","اور نہیں","بنایا ہم نے","ان کی گنتی کو","مگر","ایک آزمائش","ان لوگوں کے لیے","جنہوں نے کفر کیا","تاکہ یقین آجائے","ان لوگوں کو","جو دیے گئے","کتاب","اور زیادہ ہوجائے","ان لوگوں کا","جو ایمان لائے","ایمان","اور نہ","شک میں رہیں","وہ لوگ","جو دئیے گئے","کتاب","اور مومن","اور تاکہ کہیں","وہ لوگ","میں","جن کے دلوں (میں)","بیماری ہے","اور کافر","کیا کچھ","ارادہ کیا","اللہ نے","ساتھ اس","مثال کے","اسی طرح","بھٹکا دیتا ہے","اللہ","جس کو","چاہتا ہے","اور ہدایت دیتا ہے","جس کو","وہ چاہتا ہے","اور نہیں","جانتا","لشکروں کو","تیرے رب کے","مگر","وہی","اور نہیں","وہ","مگر","نصیحت","انسان کے لیے"]},{"number":32,"translation":"سچ کہتا ہوں قسم ہے چاند کی","words":["ہرگز نہیں","قسم ہے چاند کی"]},{"number":33,"translation":"اور رات کی جب وه پیچھے ہٹے","words":["اور رات کی","جب","وہ پلٹتی ہے"]},{"number":34,"translation":"اور صبح کی جب کہ روشن ہو جائے","words":["اور صبح کی","جب","وہ روشن ہوتی ہے"]},{"number":35,"translation":"کہ (یقیناً وه جہنم) بڑی چیزوں میں سے ایک ہے","words":["بیشک وہ","البتہ ایک ہے","بڑی چیزوں میں سے"]},{"number":36,"translation":"بنی آدم کو ڈرانے والی","words":["ڈراوا ہے","انسان کے لیے"]},{"number":37,"translation":"(یعنی) اسے جو تم میں سے آگے بڑھنا چاہے یا پیچھے ہٹنا چاہے","words":["اس کے لیے جو","چاہے","تم میں سے","کہ","آگے بڑھ جائے","یا","پیچھے رہ جائے"]},{"number":38,"translation":"ہر شخص اپنے اعمال کے بدلے میں گروی ہے","words":["ہر","نفس","بوجہ اس کے","جو اس نے کمائی کی","رھن میں ہے"]},{"number":39,"translation":"مگر دائیں ہاتھ والے","words":["مگر","والے","دائیں ہاتھ"]},{"number":40,"translation":"کہ وه بہشتوں میں (بیٹھے ہوئے) گناه گاروں سے","words":["میں","باغوں","سوال کررہے ہوں گے"]},{"number":41,"translation":"سوال کرتے ہوں گے","words":["سے","مجرموں (سے)"]},{"number":42,"translation":"تمہیں دوزخ میں کس چیز نے ڈاﻻ","words":["کیا","چیز لے گئی تم کو","میں","دوزخ"]},{"number":43,"translation":"وه جواب دیں گے کہ ہم نمازی نہ تھے","words":["وہ کہیں گے","نہ","تھے ہم","میں سے","نماز پڑھنے والوں"]},{"number":44,"translation":"نہ مسکینوں کو کھانا کھلاتے تھے","words":["اور نہ تھے ہم","ہم","کھانا کھلاتے","مسکین کو"]},{"number":45,"translation":"اور ہم بحﺚ کرنے والے (انکاریوں) کا ساتھ دے کر بحﺚ مباحثہ میں مشغول رہا کرتے تھے","words":["اور تھے ہم","ہم بحث کرتے","ساتھ","بحث کرنے والوں کے"]},{"number":46,"translation":"اور روز جزا کو جھٹلاتے تھے","words":["اور تھے ہم","ہم جھٹلاتے","روز","جزا کو"]},{"number":47,"translation":"یہاں تک کہ ہمیں موت آگئی","words":["یہاں تک کہ","آگئی ہمارے پاس","یقینی چیز۔ موت"]},{"number":48,"translation":"پس انہیں سفارش کرنے والوں کی سفارش نفع نہ دے گی","words":["تو نہ","کام آئے گی ان کو","سفارش،","سفارشیوں کی"]},{"number":49,"translation":"انہیں کیا ہو گیا ہے؟ کہ نصیحت سے منھ موڑ رہے ہیں","words":["تو کیا ہے","ان کو","سے","نصیحت سے","اعراض برتنے والے ہیں"]},{"number":50,"translation":"گویا کہ وه بِدکے ہوئے گدھے ہیں","words":["گویا کہ وہ","گدھے ہیں","بدکے ہوئے"]},{"number":51,"translation":"جو شیر سے بھاگے ہوں","words":["بھاگے ہوں","ڈر کر","شیر سے"]},{"number":52,"translation":"بلکہ ان میں سے ہر شخص چاہتا ہے کہ اسے کھلی ہوئی کتابیں دی جائیں","words":["بلکہ","چاہتا ہے","ہر","شخص","ان میں سے","کہ","وہ دیا جائے","صحیفے","کھلے۔ نشر کیے ہوئے"]},{"number":53,"translation":"ہرگز ایسا نہیں (ہوسکتا بلکہ) یہ قیامت سے بے خوف ہیں","words":["ہرگز نہیں","بلکہ","نہیں","وہ خوف رکھتے","آخرت کا"]},{"number":54,"translation":"سچی بات تو یہ ہے کہ یہ (قرآن) ایک نصیحت ہے","words":["ہرگز نہیں","بیشک وہ","ایک نصیحت ہے"]},{"number":55,"translation":"اب جو چاہے اس سے نصیحت حاصل کرے","words":["پس جو کوئی","چاہے","نصیحت حاصل کرے اس سے۔ یاد کرلے اس کو"]},{"number":56,"translation":"اور وه اس وقت نصیحت حاصل کریں گے جب اللہ تعالیٰ چاہے، وه اسی ﻻئق ہے کہ اس سے ڈریں اور اس ﻻئق بھی کہ وه بخشے","words":["اور نہ وہ","نصیحت پکڑیں گے","مگر","یہ کہ","چاہے","اللہ","وہ","حق دار ہے","اس بات کا کہ اس سے تقوی کیا جائے","اور اہل ہے","بخشش دینے کا۔ معاف کردینے کا"]}]}